LICENCE
MANIFEST.in
README.textile
setup.py
flyingsphinx/__init__.py
flyingsphinx/api.py
flyingsphinx/cli.py
flyingsphinx/configuration.py
flyingsphinx/index.py
flyingsphinx/sphinx.py
flyingsphinx.egg-info/PKG-INFO
flyingsphinx.egg-info/SOURCES.txt
flyingsphinx.egg-info/dependency_links.txt
flyingsphinx.egg-info/entry_points.txt
flyingsphinx.egg-info/requires.txt
flyingsphinx.egg-info/top_level.txt
spec/unit/api_spec.py
spec/unit/configuration_spec.py
spec/unit/flyingsphinx_spec.py
spec/unit/index_spec.py
spec/unit/sphinx_spec.py