Metadata-Version: 1.0
Name: flyingsphinx
Version: 0.2.0
Summary: Flying Sphinx Python client
Home-page: https://github.com/flying-sphinx/flying-sphinx-py
Author: Pat Allan
Author-email: pat@freelancing-gods.com
License: Copyright (c) 2012 Pat Allan
